pytorch_clip_interrogator/__init__.py
pytorch_clip_interrogator/blip.py
pytorch_clip_interrogator/clip_interrogator.py
pytorch_clip_interrogator/prompt_engineer.py
pytorch_clip_interrogator/utils.py
pytorch_clip_interrogator/vocab.py
pytorch_clip_interrogator/data/artists.txt
pytorch_clip_interrogator/data/flavors.txt
pytorch_clip_interrogator/data/mediums.txt
pytorch_clip_interrogator/data/movements.txt
pytorch_clip_interrogator/data/sites.txt
pytorch_clip_interrogator-2023.5.30.0.dist-info/LICENSE
pytorch_clip_interrogator-2023.5.30.0.dist-info/METADATA
pytorch_clip_interrogator-2023.5.30.0.dist-info/WHEEL
pytorch_clip_interrogator-2023.5.30.0.dist-info/top_level.txt
pytorch_clip_interrogator-2023.5.30.0.dist-info/zip-safe
pytorch_clip_interrogator-2023.5.30.0.dist-info/RECORD
