Metadata-Version: 2.1
Name: pytorch-clip-interrogator
Version: 2023.5.30.0
Summary: Prompt engineering tool using BLIP 1/2 + CLIP Interrogate approach.
Home-page: UNKNOWN
Author: Sergei Belousov aka BeS
Author-email: sergei.o.belousov@gmail.com
License: UNKNOWN
Platform: UNKNOWN
Classifier: Programming Language :: Python :: 3
License-File: LICENSE
Requires-Dist: wheel
Requires-Dist: torch
Requires-Dist: numpy
Requires-Dist: transformers
Requires-Dist: tokenizers
Requires-Dist: accelerate
Requires-Dist: datasets
Requires-Dist: addict (==2.4.0)
Requires-Dist: tqdm (==4.64.1)
Requires-Dist: faiss-cpu (==1.7.3)
Requires-Dist: Pillow
